{
    "language_name": "Indonesia",
  
    "dashboard": "Dasbor",
    "configs": "Konfigurasi",
    "skins": "Skin",
    "account": "Akun",
    "region": "Wilayah",
    "select_account": "Pilih Akun",
    "select_region": "Pilih Wilayah",
    "start": "Mulai",
  
    "subscription": "Langganan",
    "expiration": "Kedaluwarsa",
    "status": "Status",
    "version": "Versi",
    "refresh_data": "Segarkan Data",
    "server_status": "Status Server",
    "current_version": "Versi Saat Ini",
    "last_updated": "Terakhir Diperbarui",
    "last_version": "Versi Terakhir",
    "license": "Lisensi",
    "online": "Online",
    "offline": "Offline",
    "withissues": "Ada Masalah",
    "maintenance": "Pemeliharaan",
    "error": "Kesalahan",
    "checking": "Memeriksa...",
    "yesterday": "Kemarin",
  
    "activate_license": "Aktifkan Lisensi",
    "merge_license": "Gabungkan Lisensi",
    "renew_spkey": "Perbarui SPKey",
    "pause": "Jeda",
    "resume": "Lanjutkan",
    "reset_hwid": "Reset HWID",
  
    "3dmigoto": "3DMigoto",
    "not_installed": "Belum Terpasang",
    "installed": "Terpasang",
    "enable": "Aktifkan",
    "install": "Pasang",
    "uninstall": "Copot Pemasangan",
  
    "enabled_skins": "Skin Aktif",
    "disabled_skins": "Skin Nonaktif",
    "search_skins": "Cari skin...",
    "open": "Buka",
    "config": "Konfig",
    "disable": "Nonaktifkan",
    "enable_skin": "Aktifkan",
    "delete": "Hapus",
    "install_new_skin": "Pasang Skin Baru",
    "disable_all_skins": "Nonaktifkan Semua Skin",
  
    "launcher": "Korepi Launcher",
    "settings": "Pengaturan",
    "language": "Bahasa",
  
    "error_message": "Kesalahan",
    "success_message": "Berhasil",
    "skin_installed": "Skin berhasil dipasang!",
    "skin_deleted": "Skin berhasil dihapus!",
    "skins_disabled": "Semua skin berhasil dinonaktifkan!",
    "3dmigoto_installed": "3DMigoto berhasil dipasang!",
    "3dmigoto_uninstalled": "3DMigoto berhasil dicopot!",
  
    "injector_launched": "Injector berhasil diluncurkan.\nAkun: {0}\nWilayah: {1}",
  
    "app.title": "Korepi Launcher",
    "common.ok": "OK",
    "common.cancel": "Batal",
    "common.yes": "Ya",
    "common.no": "Tidak",
    "common.save": "Simpan",
    "common.loading": "Memuat...",
    "common.error": "Kesalahan",
    "common.success": "Berhasil",
    "common.warning": "Peringatan",
    "common.info": "Informasi",
  
    "menu.dashboard": "Dasbor",
    "menu.configs": "Konfigurasi",
    "menu.skins": "Skin",
    "menu.settings": "Pengaturan",
    "menu.about": "Tentang",
  
    "settings.language": "Bahasa",
    "settings.theme": "Tema",
    "settings.dark": "Gelap",
    "settings.light": "Terang",
  
    "error.translation": "Gagal memuat terjemahan",
    "error.load_config": "Gagal memuat konfigurasi",
  
    "days": " hari",
    "days_ago": " hari yang lalu",
    "download": "Unduh",
    "last_paused": "Terakhir Dijeda",
    "正常": "Normal",
    "暂停中": "Dijeda",
    "过期": "Kedaluwarsa",
    "封禁": "Diblokir",
  
    "config.path": "Folder Instalasi:",
    "config.open": "Buka Folder",
    "config.migotoPath": "3DMigoto:",
    "config.changePath": "Ubah Path",
    "config.openMigoto": "Buka Folder 3DMigoto",
    "launcher_settings": "Pengaturan Launcher",
    "config.uninstall": "Copot Semua",
    "config.uninstall.tooltip": "Mencopot 3DMigoto dan Korepi Launcher, dan menghapus semua file di folder instalasi dan skin.\n\nTindakan ini tidak dapat diurungkan.",
    "config.autoClose": "Minimalkan Setelah Diluncurkan",
    "config.reset": "Reset Pengaturan",
    "config.reload": "Muat Ulang Launcher",
    "config.trial": "Klaim Kunci Percobaan",
    "optional_settings": "Pengaturan Opsional",
    "config.accountManager": "Manajer Akun",
    "config.autoBackup": "Cadangkan Otomatis",
    "config.autoBackup.tooltip": "Menyimpan konfigurasi Anda secara berkala di folder cadangan.",
  
    "cfg.title": "Alat Konfigurasi",
    "cfg.transfer": "Transfer data Peta",
    "cfg.select1": "Pilih cfg.json dengan data peta",
    "cfg.select2": "Pilih cfg.json tanpa data peta",
    "cfg.transfer.success": "Transfer berhasil diselesaikan!",
    "cfg.transfer.no_map_data": "Tidak ada data peta untuk ditransfer.",
    "cfg.profile_editor": "Editor Konfigurasi",
    "cfg.select_profile": "Pilih cfg.json",
    "cfg.search": "Cari Fitur...",
    "cfg.save_changes": "Simpan Perubahan",
    "cfg.success": "Berhasil menyimpan perubahan!",
    "cfg.loaded": "Dimuat",
    "cfg.error": "Kesalahan saat menyimpan:",
  
    "utils.systemDown": "Aktivasi/Penjedaan/Melanjutkan dinonaktifkan karena downtime perangkat lunak. Periksa server untuk berita.",
    "utils.pauseCooldown1": "Sudah dijeda dalam 30 hari terakhir, tidak bisa menjeda lagi.",
    "utils.pauseCooldown2": "Dilanjutkan dalam 7 hari terakhir, tidak bisa menjeda lagi.",
    "utils.pauseCooldown3": "Dilanjutkan dalam 7 hari terakhir, tidak bisa menjeda lagi.",
    "utils.alreadyPaused": "Lisensi sudah dijeda.",
    "utils.noPause": "Lisensi ini tidak mengizinkan penjedaan.",
    "utils.notUsed": "Lisensi belum diaktifkan.",
    "utils.banned": "Lisensi telah diblokir.\nJika Anda merasa ini adalah kesalahan, silakan hubungi penjual Anda.",
    "utils.null": "Status Tidak Diketahui",
    "utils.notAllowed": "Status lisensi atau status pengguna tidak mengizinkan penjedaan.",
    "utils.empty": "Lisensi tidak memiliki waktu jeda.\nSilakan hubungi penjual Anda.",
    "utils.unpaused": "Lisensi berhasil dilanjutkan.",
    "utils.alreadyUsed": "Lisensi saat ini telah digunakan.\nTidak dapat digabungkan.",
    "utils.notPossible": "Status lisensi asli tidak memungkinkan penggabungan.",
    "utils.mergeSuccess": "Berhasil menggabungkan lisensi.",
    "utils.hwidCooldown": "HWID telah diubah dalam 7 hari terakhir, tidak bisa diubah lagi.",
    "utils.hwidSuccess": "HWID berhasil diubah.",
    "utils.hwidMismatch": "HWID tidak cocok dengan HWID saat ini.\nSilakan reset HWID Anda.",
    "utils.hiwdInvalid": "HWID tidak valid.",
    "utils.turnstile1": "Token turnstile kosong.",
    "utils.turnstile2": "Kesalahan Turnstile.",
    "utils.invalidLicense": "Lisensi yang diberikan tidak valid.",
    "utils.expired": "Lisensi telah kedaluwarsa.",
    "utils.alreadyBound": "Lisensi sudah terikat dengan pengguna lain.\nSilakan hubungi penjual Anda.",
    "utils.notClaimable": "SPKey tidak dapat diklaim.",
    "utils.noSPKey": "Tidak ada SPKey yang tersedia untuk diklaim.",
    "utils.noSPKey2": "Tidak ada SPKey terikat yang tersedia.",
    "utils.decryptFail": "Dekripsi Gagal.",
    "utils.decryptFail2": "Dekripsi lisensi gagal.",
    "utils.invalidCode": "Captcha yang Anda masukkan salah. Silakan coba lagi.",
    "utils.captchaExpired": "Captcha telah kedaluwarsa, silakan segarkan captcha.",
  
    "skins.status": "Terpasang:",
    "skins.version": "Versi:",
    "skins.enabled": "Diaktifkan",
    "skins.install": "Pasang 3DMigoto",
    "skins.uninstall": "Copot",
    "skins.search": "Cari Skin...",
    "skins.noFound": "Tidak ada mod yang ditemukan.",
    "skins.enable": "Aktifkan Skin",
    "skins.installSkin": "Pasang Skin",
    "skins.removeSkin": "Copot Skin",
    "skins.disable": "Nonaktifkan Skin",
    "skins.enableAll": "Aktifkan Semua",
    "skins.disableAll": "Nonaktifkan Semua",
    "skins.open": "Buka Folder Skin",
    "skins.open2": "Buka Folder Instalasi",
    "skins.confirmDelete": "Konfirmasi Pencopotan",
    "skins.promptDelete": "Anda yakin ingin mencopot skin ini?",
    "skins.promptEnable": "Konfirmasi Aktifkan Semua",
    "skins.confirmEnable": "Anda yakin ingin mengaktifkan semua skin?",
    "skins.confirmDisable": "Konfirmasi Nonaktifkan Semua",
    "skins.promptDisable": "Anda yakin ingin menonaktifkan semua skin?",
    "3dm.deleteSuccess": "Berhasil Dicopot",
    "3dm.uninstall": "3DMigoto berhasil dicopot.",
    "skins.enabledSkins": "Skin Aktif",
    "skins.disabledSkins": "Skin Nonaktif",
  
    "yes": "Ya",
    "no": "Tidak",
  
    "theme.selector": "Pemilih Tema",
    "themes.custom": "Tema Kustom",
    "theme.export": "Ekspor Tema",
    "theme.import": "Impor Tema",
    "category.all": "Semua",
    "category.windows": "Jendela",
    "category.controls": "Kontrol",
    "category.text": "Teks",
    "category.navigation": "Navigasi",
    "category.misc": "Lain-lain",
    "search.styles": "Cari gaya...",
    "popup.export_theme": "Ekspor Tema",
    "export.current_theme": "Ekspor pengaturan tema saat ini",
    "theme.name": "Nama Tema",
    "theme.description": "Deskripsi",
    "theme.save_path": "Path Simpan",
    "button.export": "Ekspor",
    "button.cancel": "Batal",
    "popup.export_success": "Ekspor Berhasil",
    "export.success": "Tema berhasil diekspor!",
    "export.appear_custom": "Akan muncul di bagian Tema Kustom.",
    "button.ok": "OK",
    "popup.confirm_revert": "Konfirmasi Pengembalian",
    "revert.confirmation": "Anda yakin ingin kembali ke gaya default?\nTindakan ini tidak dapat diurungkan.\n\n",
    "button.yes": "Ya",
    "button.no": "Tidak",
    "window.style_editor": "Editor Gaya",
    "button.save_style": "Simpan Perubahan Gaya",
    "button.revert_default": "Kembali ke Default",
    "style_editor.toggle": "Buka Editor Gaya",
    
    "download_complete": "Pengunduhan selesai!",
    "download.finish": "Pengunduhan Selesai",
    "download_failed": "Pengunduhan gagal.",
    "download_canceled": "Pengunduhan dibatalkan.",
    "downloading": "Mengunduh...",
    "downloading_file": "Mengunduh file...",
    "extracting_file": "Mengekstrak file...",
    "extraction_failed": "Ekstraksi gagal."
  }